fhirpathpy/__init__.py
fhirpathpy/engine/__init__.py
fhirpathpy/engine/nodes.py
fhirpathpy/engine/util.py
fhirpathpy/engine/evaluators/__init__.py
fhirpathpy/engine/invocations/__init__.py
fhirpathpy/engine/invocations/aggregate.py
fhirpathpy/engine/invocations/collections.py
fhirpathpy/engine/invocations/combining.py
fhirpathpy/engine/invocations/constants.py
fhirpathpy/engine/invocations/datetime.py
fhirpathpy/engine/invocations/equality.py
fhirpathpy/engine/invocations/existence.py
fhirpathpy/engine/invocations/filtering.py
fhirpathpy/engine/invocations/logic.py
fhirpathpy/engine/invocations/math.py
fhirpathpy/engine/invocations/misc.py
fhirpathpy/engine/invocations/navigation.py
fhirpathpy/engine/invocations/strings.py
fhirpathpy/engine/invocations/subsetting.py
fhirpathpy/engine/invocations/types.py
fhirpathpy/models/__init__.py
fhirpathpy/models/dstu2/choiceTypePaths.json
fhirpathpy/models/dstu2/path2Type.json
fhirpathpy/models/dstu2/pathsDefinedElsewhere.json
fhirpathpy/models/dstu2/type2Parent.json
fhirpathpy/models/r4/choiceTypePaths.json
fhirpathpy/models/r4/path2Type.json
fhirpathpy/models/r4/pathsDefinedElsewhere.json
fhirpathpy/models/r4/type2Parent.json
fhirpathpy/models/r5/choiceTypePaths.json
fhirpathpy/models/r5/path2Type.json
fhirpathpy/models/r5/pathsDefinedElsewhere.json
fhirpathpy/models/r5/type2Parent.json
fhirpathpy/models/stu3/choiceTypePaths.json
fhirpathpy/models/stu3/path2Type.json
fhirpathpy/models/stu3/pathsDefinedElsewhere.json
fhirpathpy/models/stu3/type2Parent.json
fhirpathpy/parser/ASTPathListener.py
fhirpathpy/parser/FHIRPath.g4
fhirpathpy/parser/README.md
fhirpathpy/parser/__init__.py
fhirpathpy/parser/generated/FHIRPath.interp
fhirpathpy/parser/generated/FHIRPath.tokens
fhirpathpy/parser/generated/FHIRPathLexer.interp
fhirpathpy/parser/generated/FHIRPathLexer.py
fhirpathpy/parser/generated/FHIRPathLexer.tokens
fhirpathpy/parser/generated/FHIRPathListener.py
fhirpathpy/parser/generated/FHIRPathParser.py
fhirpathpy-2.1.0.dist-info/licenses/LICENSE.md
fhirpathpy-2.1.0.dist-info/WHEEL
fhirpathpy-2.1.0.dist-info/METADATA
fhirpathpy-2.1.0.dist-info/RECORD
