Metadata-Version: 2.4
Name: fhirpathpy
Version: 2.1.0
Summary: FHIRPath implementation in Python
Keywords: fhir,fhirpath
Author-email: "beda.software" <fhirpath@beda.software>
Requires-Python: >=3.8
Classifier: Development Status :: 5 - Production/Stable
Classifier: Environment :: Web Environment
Classifier: Intended Audience :: Developers
Classifier: Operating System :: OS Independent
Classifier: Programming Language :: Python
Classifier: Programming Language :: Python :: 3
Classifier: Programming Language :: Python :: 3.8
Classifier: Programming Language :: Python :: 3.9
Classifier: Programming Language :: Python :: 3.10
Classifier: Programming Language :: Python :: 3.11
Classifier: Topic :: Internet :: WWW/HTTP
Classifier: Topic :: Software Development :: Libraries :: Python Modules
License-File: LICENSE.md
Requires-Dist: antlr4-python3-runtime~=4.10
Requires-Dist: python-dateutil~=2.8
Requires-Dist: pytest==7.1.1 ; extra == "test"
Requires-Dist: pyyaml==5.4 ; extra == "test"
Project-URL: Changelog, https://github.com/beda-software/fhirpath-py/blob/master/CHANGELOG.md
Project-URL: Documentation, https://github.com/beda-software/fhirpath-py#readme
Project-URL: Homepage, https://github.com/beda-software/fhirpath-py
Project-URL: Source, https://github.com/beda-software/fhirpath-py.git
Provides-Extra: test
